<?xml version="1.1" encoding="UTF-8" standalone="no"?>
<databaseChangeLog xmlns="http://www.liquibase.org/xml/ns/dbchangelog" xmlns:ext="http://www.liquibase.org/xml/ns/dbchangelog-ext" xmlns:pro="http://www.liquibase.org/xml/ns/pro" xmlns:xsi="http://www.w3.org/2001/XMLSchema-instance" xsi:schemaLocation="http://www.liquibase.org/xml/ns/dbchangelog-ext http://www.liquibase.org/xml/ns/dbchangelog/dbchangelog-ext.xsd http://www.liquibase.org/xml/ns/pro http://www.liquibase.org/xml/ns/pro/liquibase-pro-latest.xsd http://www.liquibase.org/xml/ns/dbchangelog http://www.liquibase.org/xml/ns/dbchangelog/dbchangelog-latest.xsd">
    <changeSet author="QThoi (generated)" id="1725768355370-3">
        <createTable tableName="db_images">
            <column name="id" type="BIGINT">
                <constraints nullable="false" primaryKey="true" primaryKeyName="db_imagesPK"/>
            </column>
            <column name="created_by" type="VARCHAR(255)">
                <constraints nullable="false"/>
            </column>
            <column name="created_date" type="datetime">
                <constraints nullable="false"/>
            </column>
            <column name="modified_by" type="VARCHAR(255)">
                <constraints nullable="false"/>
            </column>
            <column name="modified_date" type="datetime">
                <constraints nullable="false"/>
            </column>
            <column name="status" type="INT">
                <constraints nullable="false"/>
            </column>
            <column name="link" type="VARCHAR(255)"/>
            <column name="product_variant_id" type="BIGINT"/>
        </createTable>
    </changeSet>

    <changeSet author="QThoi (generated)" id="1725768355370-7">
        <addForeignKeyConstraint baseColumnNames="product_variant_id" baseTableName="db_images" constraintName="FKgswtl2iiv5f6xfs1mx1j9yj5w" deferrable="false" initiallyDeferred="false" referencedColumnNames="id" referencedTableName="db_product_variant" validate="true"/>
    </changeSet>
    <changeSet author="QThoi (generated)" id="1725768355370-15">
        <dropColumn columnName="image" tableName="db_product_variant"/>
    </changeSet>
</databaseChangeLog>
